chunkit/__init__.py
chunkit/config.toml
chunkit/main.py
chunkit-0.2.9.dist-info/LICENSE
chunkit-0.2.9.dist-info/METADATA
chunkit-0.2.9.dist-info/WHEEL
chunkit-0.2.9.dist-info/top_level.txt
chunkit-0.2.9.dist-info/RECORD
