Metadata-Version: 2.1
Name: chunkit
Version: 0.2.9
Summary: Convert URLs and files into LLM-friendly markdown chunks
Home-page: https://github.com/hypergrok/chunkit
Author: hypergrok
Author-email: 173556723+hypergrok@users.noreply.github.com
Project-URL: Source Code, https://github.com/hypergrok/chunkit
License-File: LICENSE
Requires-Dist: requests
Requires-Dist: html2text
Requires-Dist: beautifulsoup4
Requires-Dist: toml
